monkey_patch/__init__.py
monkey_patch.py-0.0.12.dist-info/LICENSE.txt
monkey_patch.py-0.0.12.dist-info/METADATA
monkey_patch.py-0.0.12.dist-info/WHEEL
monkey_patch.py-0.0.12.dist-info/top_level.txt
monkey_patch.py-0.0.12.dist-info/RECORD
