Metadata-Version: 2.1
Name: monkey-patch.py
Version: 0.0.12
Summary: NOTE: This project has been moved [HERE](https://pypi.org/project/tanuki.py/)
Home-page: https://github.com/monkey-patch-sdk/monkey-patch.py
Author: Jack Hopkins
Author-email: jack.hopkins@me.com
Classifier: Programming Language :: Python :: 3
Classifier: License :: OSI Approved :: MIT License
Classifier: Operating System :: OS Independent
Requires-Python: >=3.6
License-File: LICENSE.txt
Requires-Dist: tanuki.py
